gamma/__init__.py
gamma/datasets.py
gamma/loss.py
gamma/modules.py
gamma/optim.py
gamma/pipeline.py
gamma/plot.py
gamma/trainer.py
torch_gamma-0.0.4.dist-info/METADATA
torch_gamma-0.0.4.dist-info/WHEEL
torch_gamma-0.0.4.dist-info/top_level.txt
torch_gamma-0.0.4.dist-info/RECORD
